vumi_unidecode_middleware/__init__.py
vumi_unidecode_middleware/test_unidecode_middleware.py
vumi_unidecode_middleware/unidecode_middleware.py
vumi_unidecode_middleware-0.0.2.dist-info/DESCRIPTION.rst
vumi_unidecode_middleware-0.0.2.dist-info/METADATA
vumi_unidecode_middleware-0.0.2.dist-info/RECORD
vumi_unidecode_middleware-0.0.2.dist-info/WHEEL
vumi_unidecode_middleware-0.0.2.dist-info/metadata.json
vumi_unidecode_middleware-0.0.2.dist-info/top_level.txt
