Metadata-Version: 2.0
Name: vumi-unidecode-middleware
Version: 0.0.2
Summary: Vumi middleware that runs message content through unidecode
Home-page: https://github.com/praekeltfoundation/vumi-unidecode-middleware
Author: Praekelt.org
Author-email: dev@praekelt.org
License: BSD
Platform: UNKNOWN
Classifier: Development Status :: 4 - Beta
Classifier: Intended Audience :: Developers
Classifier: License :: OSI Approved :: BSD License
Classifier: Operating System :: POSIX
Classifier: Programming Language :: Python
Classifier: Programming Language :: Python :: 2.7
Classifier: Topic :: Software Development :: Libraries :: Python Modules
Requires-Dist: unidecode
Requires-Dist: vumi
